lattifai_core/__init__.py
lattifai_core/client/__init__.py
lattifai_core/client/core.py
lattifai_core/client/pyarmor_runtime_000000/__init__.py
lattifai_core/client/pyarmor_runtime_000000/pyarmor_runtime.pyd
lattifai_core/diarization/__init__.py
lattifai_core/diarization/lattifai.py
lattifai_core/diarization/match.py
lattifai_core/diarization/utils.py
lattifai_core/diarization/pyarmor_runtime_000000/__init__.py
lattifai_core/diarization/pyarmor_runtime_000000/pyarmor_runtime.pyd
lattifai_core/event/__init__.py
lattifai_core/event/audiossl_bundle.py
lattifai_core/event/lattifai.py
lattifai_core/event/model.py
lattifai_core/event/vad.py
lattifai_core/event/pyarmor_runtime_000000/__init__.py
lattifai_core/event/pyarmor_runtime_000000/pyarmor_runtime.pyd
lattifai_core/lattice/__init__.py
lattifai_core/lattice/decode.py
lattifai_core/lattice/pyarmor_runtime_000000/__init__.py
lattifai_core/lattice/pyarmor_runtime_000000/pyarmor_runtime.pyd
lattifai_core/transcription/__init__.py
lattifai_core/transcription/lattifai.py
lattifai_core/transcription/pyarmor_runtime_000000/__init__.py
lattifai_core/transcription/pyarmor_runtime_000000/pyarmor_runtime.pyd
lattifai_core-0.6.0.dist-info/METADATA
lattifai_core-0.6.0.dist-info/WHEEL
lattifai_core-0.6.0.dist-info/top_level.txt
lattifai_core-0.6.0.dist-info/RECORD
