Metadata-Version: 2.4
Name: lattifai_core
Version: 0.6.0
Summary: Lattifai: Next-generation AI-powered multimodal processing and analysis platform
Author: The Lattifai Development Team
Requires-Python: >=3.9
Requires-Dist: httpx
Requires-Dist: numba>=0.63.1
Requires-Dist: scipy<1.16.3
Requires-Dist: sebbs>=1.0.2
Requires-Dist: cryptography
Dynamic: author
Dynamic: description
Dynamic: description-content-type
Dynamic: requires-dist
Dynamic: requires-python
Dynamic: summary
